jupyterlab_myst/__init__.py
jupyterlab_myst/_version.py
jupyterlab_myst/notary.py
jupyterlab_myst/tests/__init__.py
jupyterlab_myst-2.6.0.data/data/etc/jupyter/jupyter_server_config.d/jupyterlab_myst.json
jupyterlab_myst-2.6.0.data/data/share/jupyter/labextensions/jupyterlab-myst/package.json
jupyterlab_myst-2.6.0.data/data/share/jupyter/labextensions/jupyterlab-myst/static/00b26ac825e209505639.woff2
jupyterlab_myst-2.6.0.data/data/share/jupyter/labextensions/jupyterlab-myst/static/036d4e95149b69ff9bcc.woff2
jupyterlab_myst-2.6.0.data/data/share/jupyter/labextensions/jupyterlab-myst/static/07d8e303ce4fc12b4bb5.ttf
jupyterlab_myst-2.6.0.data/data/share/jupyter/labextensions/jupyterlab-myst/static/08ce98e51b04d58945a3.ttf
jupyterlab_myst-2.6.0.data/data/share/jupyter/labextensions/jupyterlab-myst/static/0cdd387c9590a1a9f979.woff2
jupyterlab_myst-2.6.0.data/data/share/jupyter/labextensions/jupyterlab-myst/static/0d85ae7cc30f23790a7f.ttf
jupyterlab_myst-2.6.0.data/data/share/jupyter/labextensions/jupyterlab-myst/static/0f60d1b897938ec918c8.woff2
jupyterlab_myst-2.6.0.data/data/share/jupyter/labextensions/jupyterlab-myst/static/1042.15156c65f52baa091bbf.js
jupyterlab_myst-2.6.0.data/data/share/jupyter/labextensions/jupyterlab-myst/static/1109.2bbfacc8584407647210.js
jupyterlab_myst-2.6.0.data/data/share/jupyter/labextensions/jupyterlab-myst/static/11e4dc8a6471ff6d6ee5.woff
jupyterlab_myst-2.6.0.data/data/share/jupyter/labextensions/jupyterlab-myst/static/1244.dc939f00f6222a6f87a8.js
jupyterlab_myst-2.6.0.data/data/share/jupyter/labextensions/jupyterlab-myst/static/138ac28d1663b3037e9c.ttf
jupyterlab_myst-2.6.0.data/data/share/jupyter/labextensions/jupyterlab-myst/static/1483.f9a15f58696ec9630558.js
jupyterlab_myst-2.6.0.data/data/share/jupyter/labextensions/jupyterlab-myst/static/1561.57d4c3ba0d57a4f5aff7.js
jupyterlab_myst-2.6.0.data/data/share/jupyter/labextensions/jupyterlab-myst/static/1838.e743609e136e79f4d167.js
jupyterlab_myst-2.6.0.dist-info/METADATA
jupyterlab_myst-2.6.0.dist-info/WHEEL
jupyterlab_myst-2.6.0.dist-info/licenses/LICENSE
jupyterlab_myst-2.6.0.dist-info/RECORD
